{
  "title": "All the Water Between",
  "words": [
    {
      "word": "Your",
      "start": 18.62,
      "end": 19.58
    },
    {
      "word": "name",
      "start": 19.58,
      "end": 19.92
    },
    {
      "word": "fits",
      "start": 19.92,
      "end": 20.5
    },
    {
      "word": "in",
      "start": 20.5,
      "end": 20.82
    },
    {
      "word": "my",
      "start": 20.82,
      "end": 21.12
    },
    {
      "word": "head",
      "start": 21.12,
      "end": 21.76
    },
    {
      "word": "Like",
      "start": 21.76,
      "end": 23.06
    },
    {
      "word": "a",
      "start": 23.06,
      "end": 23.28
    },
    {
      "word": "coin",
      "start": 23.28,
      "end": 23.58
    },
    {
      "word": "I",
      "start": 23.58,
      "end": 24.3
    },
    {
      "word": "keep",
      "start": 24.3,
      "end": 24.68
    },
    {
      "word": "warm",
      "start": 24.68,
      "end": 25.28
    },
    {
      "word": "Across",
      "start": 25.28,
      "end": 26.68
    },
    {
      "word": "the",
      "start": 26.68,
      "end": 26.98
    },
    {
      "word": "map,",
      "start": 26.98,
      "end": 27.26
    },
    {
      "word": "across",
      "start": 27.76,
      "end": 28.2
    },
    {
      "word": "the",
      "start": 28.2,
      "end": 28.58
    },
    {
      "word": "dark",
      "start": 28.58,
      "end": 29.0
    },
    {
      "word": "You",
      "start": 29.0,
      "end": 30.64
    },
    {
      "word": "still",
      "start": 30.64,
      "end": 31.08
    },
    {
      "word": "hold",
      "start": 31.08,
      "end": 31.74
    },
    {
      "word": "your",
      "start": 31.74,
      "end": 32.14
    },
    {
      "word": "form",
      "start": 32.14,
      "end": 32.64
    },
    {
      "word": "at",
      "start": 32.64,
      "end": 33.22
    },
    {
      "word": "midnight",
      "start": 33.22,
      "end": 33.9
    },
    {
      "word": "here",
      "start": 33.9,
      "end": 34.76
    },
    {
      "word": "A",
      "start": 34.76,
      "end": 35.32
    },
    {
      "word": "morning",
      "start": 35.32,
      "end": 35.72
    },
    {
      "word": "there",
      "start": 35.72,
      "end": 36.34
    },
    {
      "word": "Still",
      "start": 36.34,
      "end": 37.52
    },
    {
      "word": "I",
      "start": 37.52,
      "end": 37.88
    },
    {
      "word": "feel",
      "start": 37.88,
      "end": 38.38
    },
    {
      "word": "the",
      "start": 38.38,
      "end": 39.0
    },
    {
      "word": "same",
      "start": 39.0,
      "end": 39.48
    },
    {
      "word": "pull",
      "start": 39.48,
      "end": 39.98
    },
    {
      "word": "Like",
      "start": 39.98,
      "end": 41.26
    },
    {
      "word": "the",
      "start": 41.26,
      "end": 41.48
    },
    {
      "word": "tide",
      "start": 41.48,
      "end": 41.96
    },
    {
      "word": "keeps",
      "start": 41.96,
      "end": 42.72
    },
    {
      "word": "its",
      "start": 42.72,
      "end": 43.16
    },
    {
      "word": "promise",
      "start": 43.16,
      "end": 43.94
    },
    {
      "word": "even",
      "start": 43.94,
      "end": 44.64
    },
    {
      "word": "when",
      "start": 44.64,
      "end": 45.24
    },
    {
      "word": "the",
      "start": 45.24,
      "end": 45.44
    },
    {
      "word": "moon",
      "start": 45.44,
      "end": 45.88
    },
    {
      "word": "is",
      "start": 45.88,
      "end": 46.74
    },
    {
      "word": "full",
      "start": 46.74,
      "end": 47.34
    },
    {
      "word": "I",
      "start": 47.34,
      "end": 48.3
    },
    {
      "word": "don't",
      "start": 48.3,
      "end": 48.76
    },
    {
      "word": "need",
      "start": 48.76,
      "end": 48.94
    },
    {
      "word": "your",
      "start": 48.94,
      "end": 49.1
    },
    {
      "word": "shoulder",
      "start": 49.1,
      "end": 49.7
    },
    {
      "word": "to",
      "start": 49.7,
      "end": 51.82
    },
    {
      "word": "know",
      "start": 51.82,
      "end": 52.16
    },
    {
      "word": "your",
      "start": 52.16,
      "end": 52.56
    },
    {
      "word": "way",
      "start": 52.56,
      "end": 53.2
    },
    {
      "word": "I",
      "start": 53.2,
      "end": 55.6
    },
    {
      "word": "don't",
      "start": 55.6,
      "end": 56.14
    },
    {
      "word": "need",
      "start": 56.14,
      "end": 56.32
    },
    {
      "word": "your",
      "start": 56.32,
      "end": 56.5
    },
    {
      "word": "footsteps",
      "start": 56.5,
      "end": 57.1
    },
    {
      "word": "to",
      "start": 57.1,
      "end": 59.26
    },
    {
      "word": "know",
      "start": 59.26,
      "end": 59.54
    },
    {
      "word": "your",
      "start": 59.54,
      "end": 59.96
    },
    {
      "word": "state",
      "start": 59.96,
      "end": 60.56
    },
    {
      "word": "All",
      "start": 61.74,
      "end": 62.62
    },
    {
      "word": "the",
      "start": 62.62,
      "end": 62.96
    },
    {
      "word": "water",
      "start": 62.96,
      "end": 63.34
    },
    {
      "word": "between",
      "start": 63.34,
      "end": 64.0
    },
    {
      "word": "can",
      "start": 64.0,
      "end": 66.38
    },
    {
      "word": "wash",
      "start": 66.38,
      "end": 66.96
    },
    {
      "word": "you",
      "start": 66.96,
      "end": 67.4
    },
    {
      "word": "out",
      "start": 67.4,
      "end": 67.88
    },
    {
      "word": "All",
      "start": 67.88,
      "end": 69.94
    },
    {
      "word": "the",
      "start": 69.94,
      "end": 70.36
    },
    {
      "word": "water",
      "start": 70.36,
      "end": 70.74
    },
    {
      "word": "between",
      "start": 70.74,
      "end": 71.42
    },
    {
      "word": "still",
      "start": 71.42,
      "end": 72.38
    },
    {
      "word": "says",
      "start": 72.38,
      "end": 73.04
    },
    {
      "word": "your",
      "start": 73.04,
      "end": 73.68
    },
    {
      "word": "name",
      "start": 73.68,
      "end": 74.16
    },
    {
      "word": "out",
      "start": 74.16,
      "end": 74.64
    },
    {
      "word": "loud",
      "start": 74.64,
      "end": 75.26
    },
    {
      "word": "You",
      "start": 75.26,
      "end": 77.36
    },
    {
      "word": "are",
      "start": 77.36,
      "end": 77.84
    },
    {
      "word": "here,",
      "start": 77.84,
      "end": 78.08
    },
    {
      "word": "you",
      "start": 78.08,
      "end": 78.56
    },
    {
      "word": "are",
      "start": 78.56,
      "end": 78.8
    },
    {
      "word": "real",
      "start": 78.8,
      "end": 79.12
    },
    {
      "word": "And",
      "start": 79.12,
      "end": 80.04
    },
    {
      "word": "the",
      "start": 80.04,
      "end": 80.36
    },
    {
      "word": "shape",
      "start": 80.36,
      "end": 80.52
    },
    {
      "word": "you",
      "start": 80.52,
      "end": 81.06
    },
    {
      "word": "leave",
      "start": 81.06,
      "end": 81.5
    },
    {
      "word": "behind",
      "start": 81.5,
      "end": 82.48
    },
    {
      "word": "All",
      "start": 84.17,
      "end": 84.7
    },
    {
      "word": "the",
      "start": 84.7,
      "end": 85.12
    },
    {
      "word": "water",
      "start": 85.12,
      "end": 85.5
    },
    {
      "word": "between",
      "start": 85.5,
      "end": 86.24
    },
    {
      "word": "still",
      "start": 86.24,
      "end": 88.52
    },
    {
      "word": "keeps",
      "start": 88.52,
      "end": 89.08
    },
    {
      "word": "us",
      "start": 89.08,
      "end": 89.56
    },
    {
      "word": "tight",
      "start": 89.56,
      "end": 90.22
    },
    {
      "word": "As",
      "start": 90.22,
      "end": 91.54
    },
    {
      "word": "I",
      "start": 91.54,
      "end": 93.44
    },
    {
      "word": "cup",
      "start": 93.44,
      "end": 93.62
    },
    {
      "word": "by",
      "start": 93.62,
      "end": 94.36
    },
    {
      "word": "the",
      "start": 94.36,
      "end": 94.82
    },
    {
      "word": "sink",
      "start": 94.82,
      "end": 95.34
    },
    {
      "word": "still",
      "start": 95.34,
      "end": 97.24
    },
    {
      "word": "set",
      "start": 97.24,
      "end": 98.02
    },
    {
      "word": "for",
      "start": 98.02,
      "end": 98.6
    },
    {
      "word": "two",
      "start": 98.6,
      "end": 99.08
    },
    {
      "word": "Some",
      "start": 99.08,
      "end": 100.38
    },
    {
      "word": "days,",
      "start": 100.38,
      "end": 100.9
    },
    {
      "word": "that",
      "start": 100.9,
      "end": 101.34
    },
    {
      "word": "little",
      "start": 101.34,
      "end": 101.78
    },
    {
      "word": "detail",
      "start": 101.78,
      "end": 102.44
    },
    {
      "word": "Is",
      "start": 102.44,
      "end": 103.66
    },
    {
      "word": "the",
      "start": 103.66,
      "end": 104.06
    },
    {
      "word": "best",
      "start": 104.06,
      "end": 104.62
    },
    {
      "word": "thing",
      "start": 104.62,
      "end": 105.0
    },
    {
      "word": "I",
      "start": 105.0,
      "end": 105.52
    },
    {
      "word": "can",
      "start": 105.52,
      "end": 105.9
    },
    {
      "word": "do",
      "start": 105.9,
      "end": 106.44
    },
    {
      "word": "I",
      "start": 106.79,
      "end": 107.24
    },
    {
      "word": "read",
      "start": 107.24,
      "end": 107.54
    },
    {
      "word": "your",
      "start": 107.54,
      "end": 107.76
    },
    {
      "word": "old",
      "start": 107.76,
      "end": 108.14
    },
    {
      "word": "messages",
      "start": 108.14,
      "end": 108.74
    },
    {
      "word": "Like",
      "start": 108.74,
      "end": 110.5
    },
    {
      "word": "prayer",
      "start": 110.5,
      "end": 110.92
    },
    {
      "word": "lines",
      "start": 110.92,
      "end": 111.82
    },
    {
      "word": "in",
      "start": 111.82,
      "end": 112.2
    },
    {
      "word": "a",
      "start": 112.2,
      "end": 112.38
    },
    {
      "word": "row",
      "start": 112.38,
      "end": 112.7
    },
    {
      "word": "Not",
      "start": 113.72,
      "end": 114.62
    },
    {
      "word": "to",
      "start": 114.62,
      "end": 115.08
    },
    {
      "word": "bring",
      "start": 115.08,
      "end": 115.38
    },
    {
      "word": "you",
      "start": 115.38,
      "end": 115.56
    },
    {
      "word": "closer",
      "start": 115.56,
      "end": 115.94
    },
    {
      "word": "Just",
      "start": 115.94,
      "end": 117.4
    },
    {
      "word": "to",
      "start": 117.4,
      "end": 117.92
    },
    {
      "word": "let",
      "start": 117.92,
      "end": 118.46
    },
    {
      "word": "the",
      "start": 118.46,
      "end": 118.76
    },
    {
      "word": "truth",
      "start": 118.76,
      "end": 119.04
    },
    {
      "word": "show",
      "start": 119.04,
      "end": 119.64
    },
    {
      "word": "I",
      "start": 121.06,
      "end": 122.1
    },
    {
      "word": "don't",
      "start": 122.1,
      "end": 122.56
    },
    {
      "word": "need",
      "start": 122.56,
      "end": 122.76
    },
    {
      "word": "the",
      "start": 122.76,
      "end": 122.94
    },
    {
      "word": "room",
      "start": 122.94,
      "end": 123.26
    },
    {
      "word": "to",
      "start": 123.26,
      "end": 123.26
    },
    {
      "word": "turn",
      "start": 123.26,
      "end": 124.14
    },
    {
      "word": "For",
      "start": 124.14,
      "end": 125.66
    },
    {
      "word": "you",
      "start": 125.66,
      "end": 126.0
    },
    {
      "word": "to",
      "start": 126.0,
      "end": 126.36
    },
    {
      "word": "be",
      "start": 126.36,
      "end": 126.7
    },
    {
      "word": "I",
      "start": 128.36,
      "end": 129.4
    },
    {
      "word": "don't",
      "start": 129.4,
      "end": 129.94
    },
    {
      "word": "need",
      "start": 129.94,
      "end": 130.1
    },
    {
      "word": "my",
      "start": 130.1,
      "end": 130.32
    },
    {
      "word": "eyes",
      "start": 130.32,
      "end": 130.78
    },
    {
      "word": "to",
      "start": 130.78,
      "end": 130.98
    },
    {
      "word": "lie",
      "start": 130.98,
      "end": 131.84
    },
    {
      "word": "You",
      "start": 131.84,
      "end": 133.12
    },
    {
      "word": "live",
      "start": 133.12,
      "end": 133.42
    },
    {
      "word": "in",
      "start": 133.42,
      "end": 133.94
    },
    {
      "word": "me",
      "start": 133.94,
      "end": 134.82
    },
    {
      "word": "All",
      "start": 135.64,
      "end": 136.46
    },
    {
      "word": "the",
      "start": 136.46,
      "end": 136.76
    },
    {
      "word": "water",
      "start": 136.76,
      "end": 137.14
    },
    {
      "word": "between",
      "start": 137.14,
      "end": 137.72
    },
    {
      "word": "can",
      "start": 137.72,
      "end": 140.16
    },
    {
      "word": "wash",
      "start": 140.16,
      "end": 140.7
    },
    {
      "word": "you",
      "start": 140.7,
      "end": 141.16
    },
    {
      "word": "out",
      "start": 141.16,
      "end": 141.76
    },
    {
      "word": "All",
      "start": 141.76,
      "end": 143.68
    },
    {
      "word": "the",
      "start": 143.68,
      "end": 144.12
    },
    {
      "word": "water",
      "start": 144.12,
      "end": 144.48
    },
    {
      "word": "between",
      "start": 144.48,
      "end": 145.2
    },
    {
      "word": "still",
      "start": 145.2,
      "end": 146.08
    },
    {
      "word": "says",
      "start": 146.08,
      "end": 146.82
    },
    {
      "word": "your",
      "start": 146.82,
      "end": 147.42
    },
    {
      "word": "name",
      "start": 147.42,
      "end": 147.94
    },
    {
      "word": "out",
      "start": 147.94,
      "end": 148.38
    },
    {
      "word": "loud",
      "start": 148.38,
      "end": 148.88
    },
    {
      "word": "You",
      "start": 150.2,
      "end": 151.08
    },
    {
      "word": "are",
      "start": 151.08,
      "end": 151.52
    },
    {
      "word": "here,",
      "start": 151.52,
      "end": 151.82
    },
    {
      "word": "you",
      "start": 151.82,
      "end": 152.18
    },
    {
      "word": "are",
      "start": 152.18,
      "end": 152.44
    },
    {
      "word": "real",
      "start": 152.44,
      "end": 152.82
    },
    {
      "word": "And",
      "start": 152.82,
      "end": 153.76
    },
    {
      "word": "the",
      "start": 153.76,
      "end": 153.96
    },
    {
      "word": "shape",
      "start": 153.96,
      "end": 154.3
    },
    {
      "word": "you",
      "start": 154.3,
      "end": 154.72
    },
    {
      "word": "leave",
      "start": 154.72,
      "end": 155.2
    },
    {
      "word": "behind",
      "start": 155.2,
      "end": 156.2
    },
    {
      "word": "All",
      "start": 157.56,
      "end": 158.44
    },
    {
      "word": "the",
      "start": 158.44,
      "end": 158.84
    },
    {
      "word": "water",
      "start": 158.84,
      "end": 159.18
    },
    {
      "word": "between",
      "start": 159.18,
      "end": 159.92
    },
    {
      "word": "still",
      "start": 159.92,
      "end": 162.26
    },
    {
      "word": "keeps",
      "start": 162.26,
      "end": 162.8
    },
    {
      "word": "us",
      "start": 162.8,
      "end": 163.26
    },
    {
      "word": "tight",
      "start": 163.26,
      "end": 164.0
    },
    {
      "word": "As",
      "start": 164.0,
      "end": 166.72
    },
    {
      "word": "the",
      "start": 166.72,
      "end": 167.08
    },
    {
      "word": "world",
      "start": 167.08,
      "end": 167.42
    },
    {
      "word": "draws",
      "start": 167.42,
      "end": 167.82
    },
    {
      "word": "lines,",
      "start": 167.82,
      "end": 168.54
    },
    {
      "word": "I",
      "start": 168.56,
      "end": 168.96
    },
    {
      "word": "draw",
      "start": 168.96,
      "end": 169.2
    },
    {
      "word": "them",
      "start": 169.2,
      "end": 169.5
    },
    {
      "word": "back",
      "start": 169.5,
      "end": 169.94
    },
    {
      "word": "with",
      "start": 169.94,
      "end": 170.42
    },
    {
      "word": "every",
      "start": 170.42,
      "end": 170.9
    },
    {
      "word": "memory",
      "start": 170.9,
      "end": 171.88
    },
    {
      "word": "And",
      "start": 171.88,
      "end": 172.52
    },
    {
      "word": "every",
      "start": 172.52,
      "end": 173.1
    },
    {
      "word": "track",
      "start": 173.1,
      "end": 173.62
    },
    {
      "word": "Time",
      "start": 173.62,
      "end": 174.34
    },
    {
      "word": "zone,",
      "start": 174.34,
      "end": 174.68
    },
    {
      "word": "time",
      "start": 175.0,
      "end": 175.4
    },
    {
      "word": "zone",
      "start": 175.4,
      "end": 175.86
    },
    {
      "word": "We",
      "start": 175.86,
      "end": 176.24
    },
    {
      "word": "do",
      "start": 176.24,
      "end": 176.48
    },
    {
      "word": "not",
      "start": 176.48,
      "end": 176.72
    },
    {
      "word": "fade",
      "start": 176.72,
      "end": 177.26
    },
    {
      "word": "Love",
      "start": 177.62,
      "end": 178.1
    },
    {
      "word": "is",
      "start": 178.1,
      "end": 178.9
    },
    {
      "word": "a",
      "start": 178.9,
      "end": 179.02
    },
    {
      "word": "real",
      "start": 179.02,
      "end": 179.32
    },
    {
      "word": "thing",
      "start": 179.32,
      "end": 179.72
    },
    {
      "word": "Even",
      "start": 179.72,
      "end": 180.4
    },
    {
      "word": "when",
      "start": 180.4,
      "end": 180.66
    },
    {
      "word": "you",
      "start": 180.66,
      "end": 180.86
    },
    {
      "word": "leave",
      "start": 180.86,
      "end": 181.24
    },
    {
      "word": "All",
      "start": 183.62,
      "end": 184.1
    },
    {
      "word": "the",
      "start": 184.1,
      "end": 184.48
    },
    {
      "word": "water",
      "start": 184.48,
      "end": 184.82
    },
    {
      "word": "between",
      "start": 184.82,
      "end": 185.42
    },
    {
      "word": "can",
      "start": 185.42,
      "end": 187.88
    },
    {
      "word": "wash",
      "start": 187.88,
      "end": 188.36
    },
    {
      "word": "you",
      "start": 188.36,
      "end": 188.86
    },
    {
      "word": "out",
      "start": 188.86,
      "end": 189.3
    },
    {
      "word": "All",
      "start": 189.3,
      "end": 191.42
    },
    {
      "word": "the",
      "start": 191.42,
      "end": 191.78
    },
    {
      "word": "water",
      "start": 191.78,
      "end": 192.22
    },
    {
      "word": "between",
      "start": 192.22,
      "end": 192.9
    },
    {
      "word": "still",
      "start": 192.9,
      "end": 193.74
    },
    {
      "word": "says",
      "start": 193.74,
      "end": 194.5
    },
    {
      "word": "your",
      "start": 194.5,
      "end": 195.1
    },
    {
      "word": "name",
      "start": 195.1,
      "end": 195.64
    },
    {
      "word": "out",
      "start": 195.64,
      "end": 196.04
    },
    {
      "word": "loud",
      "start": 196.04,
      "end": 197.0
    },
    {
      "word": "You",
      "start": 198.0,
      "end": 198.76
    },
    {
      "word": "are",
      "start": 198.76,
      "end": 199.16
    },
    {
      "word": "here,",
      "start": 199.16,
      "end": 199.48
    },
    {
      "word": "you",
      "start": 199.48,
      "end": 199.86
    },
    {
      "word": "are",
      "start": 199.86,
      "end": 200.12
    },
    {
      "word": "real",
      "start": 200.12,
      "end": 200.4
    },
    {
      "word": "And",
      "start": 200.4,
      "end": 201.4
    },
    {
      "word": "the",
      "start": 201.4,
      "end": 201.6
    },
    {
      "word": "shape",
      "start": 201.6,
      "end": 201.88
    },
    {
      "word": "you",
      "start": 201.88,
      "end": 202.34
    },
    {
      "word": "leave",
      "start": 202.34,
      "end": 202.72
    },
    {
      "word": "behind",
      "start": 202.72,
      "end": 203.78
    },
    {
      "word": "All",
      "start": 205.0,
      "end": 206.04
    },
    {
      "word": "the",
      "start": 206.04,
      "end": 206.42
    },
    {
      "word": "water",
      "start": 206.42,
      "end": 206.76
    },
    {
      "word": "between",
      "start": 206.76,
      "end": 207.6
    },
    {
      "word": "can",
      "start": 207.6,
      "end": 208.4
    },
    {
      "word": "wash",
      "start": 208.4,
      "end": 209.72
    },
    {
      "word": "you",
      "start": 209.72,
      "end": 209.92
    },
    {
      "word": "out",
      "start": 209.92,
      "end": 211.78
    },
    {
      "word": "All",
      "start": 211.78,
      "end": 213.36
    },
    {
      "word": "the",
      "start": 213.36,
      "end": 214.32
    },
    {
      "word": "water",
      "start": 214.32,
      "end": 215.02
    },
    {
      "word": "between",
      "start": 215.02,
      "end": 215.02
    },
    {
      "word": "can",
      "start": 215.02,
      "end": 215.02
    },
    {
      "word": "wash",
      "start": 215.02,
      "end": 223.26
    },
    {
      "word": "you",
      "start": 223.26,
      "end": 224.54
    },
    {
      "word": "out",
      "start": 224.54,
      "end": 226.98
    },
    {
      "word": "All",
      "start": 226.98,
      "end": 227.28
    },
    {
      "word": "the",
      "start": 227.28,
      "end": 228.58
    },
    {
      "word": "water",
      "start": 228.58,
      "end": 228.58
    },
    {
      "word": "between",
      "start": 228.58,
      "end": 228.58
    },
    {
      "word": "still",
      "start": 228.58,
      "end": 228.58
    },
    {
      "word": "says",
      "start": 228.58,
      "end": 228.58
    },
    {
      "word": "your",
      "start": 228.58,
      "end": 228.58
    },
    {
      "word": "name",
      "start": 228.58,
      "end": 228.58
    },
    {
      "word": "out",
      "start": 228.58,
      "end": 228.58
    }
  ],
  "duration": 0
}